[
    {
        "name": "alumni",
        "title": "全球校友服務網",
        "content": "<ul> <li>提供學校與校友或校友間溝通平台</li> <li>協助各單位將校友活動訊息連結於校友服務網</li> <li>各單位可提供傑出校友或校友活動新訊，編製於校友電子報</li> <li>免費申請校友信箱</li> <li>線上校友資料維護與查詢服務</li> <li>班級部落格維護</li> <li>校友電子報</li> </ul> <p>全球校友服務網: <a href='http://www.alumni.nccu.edu.tw'>http://www.alumni.nccu.edu.tw</a></p>"
    },
    {
        "name": "domestic",
        "title": "國內分會",
        "content": "<p>請前往<a href='http://www.nccualumni.club.tw/web/SG?pageID=26268&FP=47560'>總會網站</a>參閱最新分會聯絡資訊.</p> <p><a href='http://www.alumni.nccu.edu.tw'>全球校友服務網</a>亦有該項資訊.</p>"
    },
    {
        "name": "international",
        "title": "國外分會",
        "content": "<p>請前往<a href='http://www.nccualumni.club.tw/web/SG?pageID=26341&FP=47561'>總會網站</a>參閱最新分會聯絡資訊.</p> <p><a href='http://www.alumni.nccu.edu.tw'>全球校友服務網</a>亦有該項資訊.</p>"
    },
    {
        "name": "nccu",
        "title": "母校網站",
        "content": "<p>網站裡有很多母校最新的資訊, 您也可以在校園裡逛逛, 看看校園的景觀和您在學校裡的時候有什麼不同, 您也可是觀賞在校同學的活動影片, 從他們青春的身影裡也許您可以找到當年的自己.</p> <p>母校網址: <a href='http://www.nccu.edu.tw'>www.nccu.edu.tw</a></p>"
    },
    {
        "name": "nccualumni",
        "title": "校友總會",
        "content": "<p>本校校友會成立於民國二十一年本校設置大學部之後，由校長蔣中正兼任會長。政府遷台後仍沿舊貫，並置總幹事綜其事。本會經於民國三十九年五月向台北市政府登記立案，推動校友聯誼、服務、濟助之工作。歷任總幹事為吳延環、郝遇林、曹聖芬、潘振球、李煥、金克和、易勁秋、吳俊才、李鍾桂、李慶平 、鄭安國，現任總幹事為陳庚金先生。</p> <p>校友總會網站是: <a href='http://www.nccualumni.club.tw'>http://www.nccualumni.club.tw</a></p>"
    },
    {
        "name": "ncuaanc",
        "title": "主辦單位 - 北加州政大校友會",
        "content": "<p>北加州政大校友會成立將近一甲子, 2013年事該會成立六十週年慶, 成員有師長，有同學, 有眷屬，亦有遷台前法政學校的老校友。</p> <p>北加州校友會相當活躍，僑社活動，各項慶典，皆不後人；平時固定的活動有新春晚會，會員年會，中秋烤肉等等；校友會另有小型的校友社群活動，健行社每月遠足郊遊，展卷社讀書會友，網上電台為校友播放西洋老歌，古典音樂，時人訪問等等。</p> <p>北加州校友會不僅是辦活動的團體，更是愛心關懷，熱誠相顧的校友群，校友有急難，有疾病，籌款應急，噓寒問暖，奔波張羅，時有所聞. </p> <p>想多知道一些訊息, 請造訪本會網站 - <a href='http://www.ncuaanc.org'>www.ncuaanc.org</a></p>"
    },
    {
        "name": "ncuaasc",
        "title": "南加州校友會",
        "content": "<p>南加州政大校友會是海外政大校友會最大的團體, 該會活動眾多, 歡迎各地校友多來交流.</p> <p>請造訪該會網站: <a href='http://www.chengchi.org'>http://www.chengchi.org</a></p>"
    },
    {
        "name": "publish",
        "title": "1964新聞系",
        "content": "<p>1964 (民國五十三年) 畢業的新聞系校友, 設有專頁網站, 交流感情, 歡迎造訪.  大會嘉年華指派校友張莉綺為親善大使, 服務該屆校友.</p> <p>網址: <a href='http://post1964.blogspot.com/'>http://post1964.blogspot.com/</a>, 本網站是加西校友會會長, 該屆系友徐新漢製作.</p>"
    }
]
